{
  "this": 130,
  "tutorial": 26,
  "page": 3,
  "is": 193,
  "about": 13,
  "how": 12,
  "to": 632,
  "obtain": 20,
  "all": 56,
  "of": 356,
  "the": 1078,
  "achievements": 19,
  "in": 452,
  "bedrock": 23,
  "edition": 32,
  "for": 116,
  "a": 998,
  "more": 32,
  "detailed": 2,
  "list": 5,
  "each": 19,
  "achievement": 121,
  "see": 30,
  "on": 166,
  "advancements": 2,
  "java": 8,
  "advancement": 17,
  "guide": 12,
  "exclusive": 9,
  "legacy": 7,
  "console": 7,
  "and": 478,
  "intended": 3,
  "show": 3,
  "players": 4,
  "minecraft": 13,
  "contents": 1,
  "taking": 4,
  "inventory": 22,
  "open": 6,
  "your": 99,
  "getting": 16,
  "wood": 15,
  "punch": 3,
  "tree": 7,
  "until": 37,
  "block": 94,
  "pops": 3,
  "out": 22,
  "benchmaking": 2,
  "craft": 101,
  "crafting": 127,
  "table": 37,
  "with": 245,
  "four": 13,
  "blocks": 99,
  "wooden": 18,
  "planks": 49,
  "time": 27,
  "mine": 21,
  "use": 120,
  "sticks": 15,
  "make": 70,
  "pickaxe": 25,
  "hot": 5,
  "topic": 3,
  "construct": 13,
  "furnace": 28,
  "eight": 4,
  "cobblestone": 29,
  "acquire": 9,
  "hardware": 2,
  "smelt": 12,
  "an": 165,
  "iron": 107,
  "ingot": 39,
  "farm": 8,
  "hoe": 6,
  "bake": 4,
  "bread": 5,
  "turn": 14,
  "wheat": 24,
  "into": 68,
  "lie": 3,
  "cake": 7,
  "using": 81,
  "sugar": 18,
  "milk": 7,
  "eggs": 5,
  "upgrade": 6,
  "better": 7,
  "delicious": 2,
  "fish": 21,
  "catch": 4,
  "cook": 11,
  "rail": 6,
  "travel": 11,
  "by": 134,
  "minecart": 17,
  "point": 11,
  "at": 87,
  "least": 23,
  "single": 14,
  "direction": 10,
  "from": 149,
  "where": 16,
  "you": 520,
  "started": 4,
  "strike": 3,
  "sword": 22,
  "monster": 12,
  "hunter": 6,
  "attack": 25,
  "destroy": 7,
  "cow": 7,
  "tipper": 2,
  "harvest": 2,
  "some": 43,
  "leather": 28,
  "when": 57,
  "pigs": 2,
  "fly": 14,
  "saddle": 6,
  "ride": 9,
  "pig": 11,
  "then": 65,
  "have": 102,
  "get": 157,
  "hurt": 8,
  "fall": 21,
  "damage": 31,
  "while": 32,
  "riding": 2,
  "it": 292,
  "sniper": 2,
  "duel": 2,
  "kill": 58,
  "skeleton": 32,
  "arrow": 11,
  "than": 19,
  "meters": 4,
  "diamonds": 18,
  "tools": 7,
  "nether": 54,
  "portal": 48,
  "return": 4,
  "sender": 2,
  "ghast": 20,
  "fireball": 15,
  "fire": 19,
  "relieve": 2,
  "blaze": 26,
  "its": 14,
  "rod": 18,
  "local": 2,
  "brewery": 2,
  "brew": 10,
  "potion": 46,
  "end": 50,
  "enter": 10,
  "enderdragon": 4,
  "enchanter": 2,
  "enchantment": 12,
  "overkill": 2,
  "deal": 10,
  "nine": 3,
  "hearts": 4,
  "hit": 35,
  "librarian": 3,
  "build": 22,
  "bookshelves": 3,
  "improve": 2,
  "adventuring": 3,
  "discover": 2,
  "biomes": 54,
  "beginning": 7,
  "spawn": 54,
  "wither": 28,
  "beaconator": 2,
  "create": 16,
  "fully": 6,
  "power": 11,
  "beacon": 6,
  "repopulation": 2,
  "breed": 12,
  "two": 22,
  "cows": 8,
  "throw": 22,
  "another": 25,
  "player": 16,
  "overpowered": 2,
  "eat": 16,
  "enchanted": 27,
  "apple": 20,
  "moar": 2,
  "one": 72,
  "type": 11,
  "tool": 9,
  "dispense": 2,
  "dispenser": 4,
  "leader": 2,
  "pack": 7,
  "befriend": 4,
  "five": 12,
  "wolves": 6,
  "pork": 6,
  "chop": 4,
  "passing": 2,
  "play": 7,
  "days": 9,
  "haggler": 2,
  "or": 249,
  "spend": 5,
  "emeralds": 18,
  "trading": 12,
  "villagers": 21,
  "wandering": 7,
  "trader": 16,
  "pot": 11,
  "planter": 2,
  "place": 87,
  "flower": 7,
  "it's": 8,
  "sign": 5,
  "oak": 11,
  "belly": 2,
  "stop": 5,
  "starvation": 2,
  "rotten": 5,
  "flesh": 5,
  "shearful": 2,
  "day": 7,
  "shears": 9,
  "wool": 14,
  "sheep": 8,
  "rainbow": 2,
  "collection": 3,
  "gather": 2,
  "colors": 3,
  "stayin": 2,
  "frosty": 2,
  "swim": 8,
  "lava": 22,
  "having": 9,
  "resistance": 9,
  "effect": 18,
  "chestful": 2,
  "chest": 33,
  "renewable": 3,
  "energy": 2,
  "trunks": 2,
  "charcoal": 10,
  "body": 3,
  "guard": 2,
  "golem": 10,
  "man": 2,
  "wear": 10,
  "full": 12,
  "set": 10,
  "armor": 47,
  "zombie": 37,
  "doctor": 3,
  "cure": 3,
  "villager": 53,
  "lion": 2,
  "gain": 5,
  "trust": 3,
  "ocelot": 3,
  "archer": 2,
  "creeper": 16,
  "arrows": 8,
  "tie": 2,
  "dye": 45,
  "outfit": 2,
  "cauldron": 7,
  "unique": 2,
  "pieces": 3,
  "trampoline": 2,
  "bounce": 3,
  "upward": 11,
  "off": 13,
  "slime": 9,
  "camouflage": 2,
  "mob": 37,
  "wearing": 5,
  "same": 12,
  "head": 11,
  "map": 36,
  "room": 4,
  "explored": 3,
  "adjacent": 2,
  "items": 12,
  "item": 24,
  "frames": 6,
  "square": 7,
  "freight": 2,
  "station": 3,
  "hopper": 6,
  "move": 13,
  "everything": 5,
  "connect": 2,
  "chests": 32,
  "hoppers": 3,
  "taste": 2,
  "own": 7,
  "medicine": 2,
  "poison": 5,
  "witch": 8,
  "splash": 16,
  "inception": 2,
  "push": 5,
  "piston": 29,
  "pull": 4,
  "original": 4,
  "that": 96,
  "up": 67,
  "tame": 6,
  "horse": 13,
  "artificial": 2,
  "selection": 2,
  "mule": 2,
  "donkey": 5,
  "free": 4,
  "diver": 2,
  "stay": 11,
  "underwater": 26,
  "minutes": 23,
  "rabbit": 11,
  "season": 2,
  "meat": 4,
  "deep": 33,
  "defeat": 9,
  "elder": 11,
  "guardian": 9,
  "dry": 7,
  "spell": 2,
  "sponge": 4,
  "super": 4,
  "fuel": 27,
  "need": 90,
  "mint": 2,
  "collect": 32,
  "dragons": 2,
  "breath": 8,
  "glass": 22,
  "bottle": 29,
  "beam": 3,
  "me": 8,
  "teleport": 5,
  "over": 8,
  "ender": 32,
  "pearl": 10,
  "again": 13,
  "respawn": 4,
  "great": 3,
  "view": 3,
  "here": 5,
  "levitate": 3,
  "attacks": 3,
  "shulker": 18,
  "sonic": 2,
  "elytra": 14,
  "through": 12,
  "gap": 7,
  "moving": 5,
  "faster": 7,
  "m": 2,
  "s": 5,
  "treasure": 20,
  "cartographer": 9,
  "revealed": 2,
  "structure": 5,
  "organizational": 2,
  "wizard": 2,
  "name": 10,
  "box": 9,
  "anvil": 6,
  "cheating": 2,
  "death": 5,
  "totem": 9,
  "undying": 9,
  "cheat": 2,
  "feeling": 5,
  "ill": 2,
  "evoker": 8,
  "let": 7,
  "go": 23,
  "frost": 3,
  "walker": 3,
  "boots": 13,
  "walk": 11,
  "frozen": 16,
  "water": 76,
  "ocean": 80,
  "so": 83,
  "i": 3,
  "got": 8,
  "going": 8,
  "lead": 14,
  "caravan": 4,
  "containing": 2,
  "llamas": 11,
  "atlantis": 2,
  "find": 110,
  "ruin": 3,
  "sail": 2,
  "seas": 2,
  "visit": 5,
  "castaway": 2,
  "nothing": 4,
  "but": 44,
  "dried": 18,
  "kelp": 18,
  "three": 13,
  "in-game": 4,
  "ahoy": 2,
  "shipwreck": 6,
  "i'm": 2,
  "marine": 2,
  "biologist": 2,
  "bucket": 28,
  "gold": 25,
  "dig": 14,
  "buried": 10,
  "sleep": 7,
  "fishes": 2,
  "alternative": 4,
  "do": 20,
  "barrel": 2,
  "roll": 2,
  "riptide": 8,
  "give": 14,
  "yourself": 17,
  "boost": 4,
  "pickle": 7,
  "sea": 17,
  "pickles": 5,
  "group": 2,
  "echolocation": 2,
  "feed": 5,
  "dolphin": 6,
  "moskstraumen": 2,
  "activate": 9,
  "conduit": 9,
  "top": 25,
  "world": 28,
  "scaffolding": 15,
  "limit": 15,
  "been": 8,
  "receive": 6,
  "gift": 7,
  "tamed": 11,
  "cat": 12,
  "morning": 3,
  "zoologist": 2,
  "pandas": 5,
  "bamboo": 17,
  "fruit": 4,
  "loom": 4,
  "banner": 6,
  "stencil": 2,
  "plethora": 2,
  "cats": 11,
  "twenty": 2,
  "stray": 8,
  "beast": 2,
  "ravager": 4,
  "buy": 6,
  "low": 4,
  "sell": 8,
  "high": 13,
  "trade": 18,
  "best": 12,
  "possible": 11,
  "price": 4,
  "disenchanted": 3,
  "grindstone": 5,
  "experience": 5,
  "we're": 2,
  "being": 7,
  "attacked": 3,
  "trigger": 5,
  "pillager": 21,
  "raid": 11,
  "sound": 7,
  "alarm": 2,
  "ring": 2,
  "bell": 6,
  "village": 33,
  "after": 26,
  "has": 21,
  "i've": 2,
  "bad": 10,
  "captain": 3,
  "master": 2,
  "stew": 6,
  "someone": 2,
  "suspicious": 13,
  "bee": 22,
  "our": 7,
  "guest": 5,
  "campfire": 14,
  "honey": 19,
  "beehive": 10,
  "without": 18,
  "aggravating": 2,
  "bees": 20,
  "total": 3,
  "beelocation": 2,
  "nest": 22,
  "inside": 21,
  "silk": 15,
  "touch": 16,
  "sticky": 10,
  "situation": 2,
  "slide": 2,
  "down": 25,
  "slow": 4,
  "bullseye": 4,
  "target": 6,
  "cover": 2,
  "debris": 3,
  "netherite": 21,
  "oooh": 2,
  "shiny": 2,
  "distract": 2,
  "piglin": 14,
  "tourist": 2,
  "destination": 2,
  "whatever": 2,
  "floats": 2,
  "goat": 10,
  "boat": 17,
  "float": 2,
  "wax": 7,
  "apply": 5,
  "remove": 5,
  "copper": 24,
  "healing": 4,
  "friendship": 2,
  "team": 2,
  "axolotl": 15,
  "win": 2,
  "fight": 8,
  "caves": 17,
  "cliffs": 2,
  "bottom": 9,
  "survive": 3,
  "step": 12,
  "shaft": 9,
  "pillar": 17,
  "jump": 20,
  "method": 19,
  "star": 4,
  "height": 9,
  "music": 17,
  "meadows": 2,
  "come": 2,
  "alive": 3,
  "jukebox": 9,
  "feels": 2,
  "like": 52,
  "home": 3,
  "take": 13,
  "strider": 11,
  "loooong": 2,
  "lake": 4,
  "overworld": 16,
  "spreads": 2,
  "next": 40,
  "catalyst": 10,
  "birthday": 2,
  "song": 2,
  "allay": 8,
  "drop": 22,
  "noteblock": 2,
  "powers": 2,
  "combined": 4,
  "froglights": 5,
  "sneak": 6,
  "sculk": 7,
  "sensor": 3,
  "triggering": 2,
  "planting": 2,
  "past": 3,
  "plant": 5,
  "any": 103,
  "sniffer": 4,
  "seed": 5,
  "careful": 3,
  "restoration": 2,
  "decorated": 7,
  "pottery": 6,
  "sherds": 7,
  "smithing": 15,
  "style": 2,
  "these": 32,
  "templates": 4,
  "once": 44,
  "spire": 3,
  "snout": 3,
  "rib": 3,
  "ward": 3,
  "silence": 3,
  "vex": 4,
  "tide": 3,
  "wayfinder": 3,
  "revaulting": 2,
  "unlock": 3,
  "ominous": 29,
  "vault": 4,
  "trial": 44,
  "key": 6,
  "crafters": 4,
  "be": 219,
  "near": 23,
  "crafter": 10,
  "crafts": 2,
  "who": 2,
  "needs": 4,
  "rockets": 4,
  "goal": 3,
  "wind": 7,
  "charge": 16,
  "launch": 4,
  "over-overkill": 3,
  "mace": 5,
  "heart": 16,
  "transplanter": 2,
  "creaking": 18,
  "between": 3,
  "aligned": 2,
  "pale": 10,
  "logs": 12,
  "hydrated": 3,
  "kabob": 2,
  "mobs": 24,
  "spear": 4,
  "my": 2,
  "ears": 2,
  "disc": 10,
  "playstation": 17,
  "change": 4,
  "sheets": 2,
  "bed": 11,
  "different": 15,
  "color": 6,
  "awarded": 6,
  "trophies": 13,
  "downloadable": 2,
  "also": 99,
  "navigation": 5,
  "edit": 560,
  "source": 287,
  "there": 38,
  "are": 108,
  "devices": 1,
  "before": 16,
  "discontinuation": 1,
  "were": 2,
  "xbox": 7,
  "wii": 3,
  "u": 3,
  "editions": 4,
  "nintendo": 6,
  "switch": 5,
  "vita": 2,
  "new": 8,
  "number": 3,
  "per": 4,
  "version": 2,
  "first": 47,
  "as": 89,
  "well": 7,
  "easiest": 15,
  "keyboard": 1,
  "press": 9,
  "e": 2,
  "controller": 2,
  "series": 1,
  "x": 5,
  "tap": 1,
  "hotbar": 1,
  "large": 5,
  "screen": 2,
  "will": 110,
  "pop": 1,
  "menu": 2,
  "requires": 8,
  "hold": 6,
  "button": 6,
  "facing": 4,
  "breaks": 2,
  "pick": 6,
  "found": 66,
  "trees": 4,
  "which": 52,
  "very": 24,
  "easy": 20,
  "most": 17,
  "excluding": 1,
  "desert": 22,
  "badlands": 7,
  "can": 303,
  "swamp": 7,
  "huts": 2,
  "villages": 21,
  "outposts": 7,
  "woodland": 23,
  "mansions": 15,
  "log": 9,
  "dropped": 14,
  "walking": 2,
  "part": 4,
  "long": 9,
  "didn't": 5,
  "start": 13,
  "biome": 25,
  "just": 13,
  "look": 6,
  "around": 12,
  "grid": 7,
  "right-hand": 1,
  "corner": 1,
  "slots": 5,
  "click": 5,
  "appear": 7,
  "them": 57,
  "if": 87,
  "turned": 1,
  "bonus": 1,
  "created": 1,
  "good": 4,
  "chance": 21,
  "contains": 1,
  "both": 6,
  "probably": 3,
  "won't": 2,
  "finally": 6,
  "put": 21,
  "container": 1,
  "plank": 1,
  "instead": 7,
  "alternatively": 25,
  "recipe": 132,
  "book": 16,
  "ground": 17,
  "holding": 10,
  "hand": 7,
  "follow": 5,
  "below": 18,
  "note": 14,
  "done": 8,
  "ingredients": 126,
  "stick": 27,
  "now": 15,
  "arrange": 6,
  "may": 18,
  "order": 2,
  "enough": 17,
  "stone": 21,
  "becomes": 4,
  "normal": 12,
  "exposed": 4,
  "sides": 3,
  "hills": 7,
  "ravines": 2,
  "cave": 9,
  "ravine": 1,
  "wary": 1,
  "hostile": 6,
  "such": 14,
  "zombies": 8,
  "skeletons": 7,
  "might": 7,
  "y": 11,
  "blackstone": 6,
  "deepslate": 7,
  "although": 8,
  "chances": 3,
  "finding": 9,
  "blob": 1,
  "picking": 2,
  "slim": 1,
  "commonly": 3,
  "basalt": 5,
  "deltas": 3,
  "other": 29,
  "stone-tier": 4,
  "ingots": 18,
  "ore": 18,
  "generates": 11,
  "almost": 1,
  "except": 8,
  "layers": 2,
  "common": 9,
  "easily": 17,
  "mountains": 4,
  "they": 45,
  "nearby": 12,
  "main": 4,
  "ways": 8,
  "surface": 9,
  "either": 18,
  "side": 9,
  "hill": 1,
  "mountain": 4,
  "because": 10,
  "often": 7,
  "monsters": 2,
  "not": 43,
  "recommended": 24,
  "weapons": 2,
  "much": 6,
  "safer": 3,
  "no": 15,
  "surfaces": 1,
  "could": 6,
  "mineshaft": 1,
  "daring": 1,
  "adventurous": 1,
  "few": 13,
  "torches": 1,
  "search": 2,
  "usually": 6,
  "quickly": 6,
  "walls": 3,
  "expose": 1,
  "lot": 7,
  "don't": 24,
  "anything": 3,
  "raw": 26,
  "unless": 3,
  "mined": 2,
  "case": 4,
  "drops": 15,
  "along": 4,
  "coal": 2,
  "seconds": 6,
  "yields": 1,
  "smelting": 21,
  "lucky": 1,
  "blacksmiths": 4,
  "armorer's": 2,
  "house": 6,
  "toolsmith's": 2,
  "temples": 8,
  "rooms": 7,
  "mineshafts": 7,
  "jungle": 19,
  "pyramids": 4,
  "shipwrecks": 12,
  "treasures": 3,
  "strongholds": 6,
  "chambers": 22,
  "fortresses": 3,
  "bastions": 3,
  "cities": 15,
  "nuggets": 3,
  "ruined": 10,
  "portals": 5,
  "taiga": 14,
  "houses": 6,
  "nugget": 2,
  "golems": 2,
  "killed": 14,
  "difficulty": 4,
  "beyond": 2,
  "peaceful": 2,
  "back": 18,
  "try": 16,
  "deals": 3,
  "lots": 2,
  "inexperienced": 1,
  "husks": 1,
  "small": 6,
  "obtained": 32,
  "swords": 1,
  "chainmail": 2,
  "bartering": 10,
  "transfer": 1,
  "further": 1,
  "made": 5,
  "many": 7,
  "useful": 3,
  "hoes": 1,
  "crafted": 22,
  "break": 16,
  "several": 5,
  "short": 3,
  "grass": 4,
  "seeds": 7,
  "longer": 4,
  "dirt": 7,
  "podzol": 1,
  "farmland": 4,
  "wait": 15,
  "grow": 4,
  "alternately": 1,
  "bone": 4,
  "meal": 3,
  "cause": 3,
  "way": 49,
  "generated": 6,
  "loot": 13,
  "achievement's": 1,
  "reference": 1,
  "video": 2,
  "game": 9,
  "spawned": 8,
  "meme": 1,
  "phrase": 1,
  "following": 4,
  "egg": 8,
  "chicken": 3,
  "buckets": 8,
  "cane": 8,
  "mining": 8,
  "spawning": 9,
  "middle": 5,
  "plains": 19,
  "forest": 22,
  "lay": 1,
  "collecting": 2,
  "under": 12,
  "prevent": 7,
  "attacking": 2,
  "witches": 5,
  "hard": 4,
  "growing": 2,
  "sure": 27,
  "cobbled": 1,
  "swimming": 4,
  "fist": 2,
  "salmon": 7,
  "cod": 8,
  "fishing": 14,
  "string": 8,
  "killing": 19,
  "spiders": 2,
  "destroying": 1,
  "cobwebs": 1,
  "ruins": 18,
  "drowned": 14,
  "fisherman": 2,
  "bobber": 3,
  "bubbles": 1,
  "dips": 1,
  "reel": 1,
  "junk": 2,
  "information": 4,
  "rails": 9,
  "stacks": 5,
  "farms": 3,
  "veins": 1,
  "fast": 8,
  "resources": 3,
  "continuous": 1,
  "track": 6,
  "distance": 7,
  "relatively": 3,
  "flat": 2,
  "terrain": 6,
  "avoid": 5,
  "rivers": 6,
  "oceans": 13,
  "building": 12,
  "cross": 3,
  "waterlog": 1,
  "risk": 3,
  "drowning": 4,
  "steep": 1,
  "speed": 5,
  "pass": 2,
  "replace": 1,
  "powered": 6,
  "redstone": 21,
  "torch": 4,
  "dust": 11,
  "level": 17,
  "farmed": 3,
  "afterward": 2,
  "leaving": 1,
  "does": 8,
  "allow": 1,
  "repeatedly": 1,
  "loop": 1,
  "section": 2,
  "gradual": 1,
  "decline": 1,
  "gravity": 1,
  "materials": 6,
  "blade": 1,
  "work": 5,
  "too": 7,
  "count": 6,
  "complete": 7,
  "bogged": 1,
  "breeze": 7,
  "camel": 1,
  "husk": 2,
  "verify": 4,
  "spider": 8,
  "dragon": 17,
  "enderman": 2,
  "endermite": 1,
  "hoglin": 3,
  "magma": 18,
  "cube": 4,
  "parched": 1,
  "phantom": 2,
  "brute": 1,
  "silverfish": 2,
  "vindicator": 1,
  "zoglin": 1,
  "nautilus": 4,
  "zombified": 2,
  "wardens": 2,
  "horses": 8,
  "despite": 1,
  "can't": 8,
  "bare": 1,
  "hands": 1,
  "weapon": 6,
  "bow": 13,
  "axe": 8,
  "decrease": 1,
  "earn": 4,
  "easy-to-kill": 1,
  "particles": 7,
  "mooshroom": 2,
  "llama": 4,
  "light": 14,
  "donkeys": 3,
  "only": 38,
  "savanna": 11,
  "red": 6,
  "mooshrooms": 3,
  "mushroom": 4,
  "fields": 2,
  "spawns": 5,
  "always": 9,
  "itself": 2,
  "uncommon": 1,
  "wander": 2,
  "bit": 5,
  "you'll": 2,
  "able": 1,
  "stand": 14,
  "left-click": 1,
  "beef": 1,
  "did": 3,
  "rabbits": 3,
  "hides": 1,
  "carrot": 11,
  "saddles": 1,
  "max-level": 1,
  "leatherworker": 2,
  "description": 3,
  "damaged": 1,
  "must": 14,
  "diagonally": 1,
  "above": 17,
  "should": 23,
  "cliff": 4,
  "normally": 1,
  "would": 1,
  "trapdoor": 6,
  "fence": 2,
  "gate": 2,
  "kind": 1,
  "opening": 2,
  "mechanism": 2,
  "shot": 1,
  "away": 9,
  "horizontally": 4,
  "trap": 6,
  "smallest": 2,
  "area": 8,
  "fences": 1,
  "nighttime": 1,
  "doesn't": 16,
  "burn": 3,
  "helmet": 7,
  "daylight": 3,
  "however": 4,
  "eventually": 4,
  "ensure": 1,
  "despawn": 2,
  "tag": 1,
  "coordinates": 6,
  "settings": 2,
  "shoot": 7,
  "degree": 2,
  "angle": 2,
  "toward": 4,
  "reduce": 2,
  "fov": 1,
  "aim": 3,
  "tries": 1,
  "correctly": 4,
  "projectile": 8,
  "weaken": 1,
  "certain": 5,
  "times": 5,
  "was": 3,
  "last": 3,
  "diamond": 40,
  "twice": 1,
  "shooting": 3,
  "charged": 4,
  "iv": 2,
  "v": 5,
  "health": 3,
  "underground": 7,
  "various": 3,
  "directly": 7,
  "ores": 1,
  "rare": 9,
  "branch": 1,
  "exploring": 4,
  "rarely": 4,
  "generate": 29,
  "vaults": 6,
  "brush": 2,
  "excavate": 1,
  "sand": 21,
  "fix": 5,
  "obsidian": 14,
  "placed": 8,
  "casting": 1,
  "upright": 1,
  "else": 2,
  "question": 1,
  "marks": 1,
  "including": 1,
  "air": 7,
  "entire": 1,
  "frame": 7,
  "depending": 2,
  "broken": 3,
  "easier": 5,
  "harder": 4,
  "crying": 2,
  "corners": 2,
  "works": 3,
  "placing": 5,
  "regular": 3,
  "gaps": 1,
  "contain": 5,
  "help": 8,
  "likely": 2,
  "anyway": 1,
  "flint": 10,
  "steel": 5,
  "even": 11,
  "decide": 1,
  "piece": 4,
  "anywhere": 4,
  "gravel": 6,
  "fletcher's": 1,
  "flammable": 1,
  "lightning": 1,
  "those": 7,
  "methods": 8,
  "correct": 4,
  "size": 1,
  "teleported": 1,
  "prepared": 2,
  "moment": 1,
  "foot": 3,
  "ghasts": 3,
  "soul": 17,
  "valley": 4,
  "wastes": 2,
  "shoots": 2,
  "comes": 6,
  "close": 6,
  "send": 1,
  "flying": 12,
  "reflected": 1,
  "goes": 1,
  "roughly": 1,
  "crosshair": 1,
  "pointing": 3,
  "position": 2,
  "reflect": 1,
  "endangering": 1,
  "face": 3,
  "slightly": 3,
  "spam-clicking": 2,
  "outside": 1,
  "hitbox": 2,
  "fail": 2,
  "flies": 2,
  "dealing": 3,
  "beneficial": 1,
  "window": 1,
  "dangerous": 3,
  "unskilled": 1,
  "snowball": 1,
  "moves": 1,
  "used": 6,
  "accurately": 1,
  "default": 1,
  "wolf": 2,
  "looting": 4,
  "increases": 1,
  "amount": 5,
  "rods": 6,
  "iii": 5,
  "warned": 2,
  "blazes": 3,
  "enemies": 2,
  "melee": 6,
  "addition": 1,
  "lighting": 1,
  "especially": 2,
  "deadly": 1,
  "potions": 9,
  "piglins": 4,
  "tips": 6,
  "fortress": 6,
  "inhabitants": 1,
  "check": 1,
  "defeating": 27,
  "brewing": 15,
  "stands": 5,
  "churches": 1,
  "igloos": 3,
  "basement": 2,
  "ships": 3,
  "outline": 2,
  "slot": 12,
  "actual": 1,
  "ingredient": 2,
  "left": 4,
  "powder": 9,
  "lower": 2,
  "stand's": 1,
  "findable": 1,
  "eyes": 8,
  "fill": 9,
  "activated": 2,
  "pearls": 4,
  "endermen": 3,
  "expert-level": 1,
  "cleric": 1,
  "fake": 1,
  "trapped": 1,
  "triggers": 1,
  "tnt": 4,
  "opened": 1,
  "barrels": 1,
  "feasible": 1,
  "early": 2,
  "warped": 4,
  "info": 2,
  "additional": 2,
  "ones": 4,
  "needed": 4,
  "stronghold": 11,
  "cases": 2,
  "given": 4,
  "lose": 2,
  "reaching": 2,
  "preferably": 5,
  "spot": 5,
  "reach": 6,
  "bricks": 7,
  "die": 4,
  "attempt": 4,
  "hardcore": 3,
  "mode": 5,
  "beat": 1,
  "since": 12,
  "cannot": 7,
  "exit": 8,
  "proper": 1,
  "their": 11,
  "enjoy": 1,
  "poem": 1,
  "esc": 1,
  "skip": 3,
  "credits": 1,
  "obtaining": 7,
  "books": 4,
  "paper": 13,
  "mules": 1,
  "hoglins": 1,
  "foxes": 1,
  "fox": 2,
  "sometimes": 1,
  "upon": 1,
  "hide": 2,
  "naturally": 7,
  "bodies": 1,
  "lakes": 2,
  "cartographer's": 1,
  "libraries": 3,
  "bookshelf": 2,
  "library": 1,
  "disenchanting": 1,
  "ancient": 15,
  "enchant": 5,
  "bane": 1,
  "arthropods": 1,
  "smite": 3,
  "sharpness": 2,
  "together": 1,
  "sword's": 1,
  "base": 1,
  "hp": 2,
  "trident": 10,
  "impaling": 2,
  "strength": 3,
  "increased": 2,
  "smash": 1,
  "achieved": 4,
  "setting": 6,
  "beach": 3,
  "birch": 6,
  "cherry": 5,
  "grove": 7,
  "cold": 10,
  "dark": 11,
  "lukewarm": 6,
  "dripstone": 2,
  "eroded": 1,
  "peaks": 5,
  "river": 4,
  "ice": 5,
  "spikes": 1,
  "jagged": 2,
  "lush": 4,
  "mangrove": 4,
  "meadow": 6,
  "old": 10,
  "growth": 7,
  "pine": 2,
  "spruce": 2,
  "plateau": 4,
  "snowy": 13,
  "slopes": 3,
  "sparse": 3,
  "stony": 5,
  "shore": 4,
  "sunflower": 4,
  "warm": 12,
  "windswept": 5,
  "gravelly": 1,
  "wooded": 3,
  "visited": 2,
  "worlds": 3,
  "creating": 10,
  "every": 11,
  "template": 4,
  "soil": 4,
  "t": 2,
  "shape": 1,
  "skulls": 2,
  "line": 1,
  "arms": 2,
  "acquired": 2,
  "wich": 1,
  "immediately": 2,
  "you're": 7,
  "within": 7,
  "withers": 1,
  "nor": 1,
  "harm": 1,
  "explodes": 1,
  "explosion": 2,
  "violent": 1,
  "summon": 1,
  "preparation": 1,
  "what": 4,
  "expect": 1,
  "prepare": 5,
  "pages": 2,
  "extensive": 1,
  "full-size": 1,
  "pyramid": 1,
  "emerald": 7,
  "fastest": 4,
  "layer": 6,
  "sky": 5,
  "multiplayer": 4,
  "picked": 1,
  "golden": 34,
  "rarest": 1,
  "bastion": 8,
  "remnants": 2,
  "highest": 2,
  "city": 10,
  "fairly": 1,
  "simple": 3,
  "lastly": 4,
  "remaining": 1,
  "shovel": 4,
  "night": 7,
  "multiple": 5,
  "deeper": 3,
  "packs": 5,
  "bones": 2,
  "porkchop": 5,
  "smoker": 7,
  "stripped": 5,
  "right": 7,
  "cooked": 3,
  "aspect": 1,
  "flame": 1,
  "burning": 1,
  "eating": 3,
  "equal": 2,
  "hours": 2,
  "real": 1,
  "afk": 2,
  "pool": 4,
  "half": 4,
  "skipped": 1,
  "sleeping": 2,
  "played": 2,
  "far": 5,
  "farmer": 9,
  "trades": 3,
  "potato": 2,
  "beetroot": 2,
  "offers": 1,
  "extra": 5,
  "crops": 1,
  "already": 2,
  "ton": 1,
  "expanding": 1,
  "butcher": 1,
  "porkchops": 1,
  "steps": 2,
  "clay": 6,
  "balls": 1,
  "ball": 2,
  "brick": 1,
  "beautiful": 1,
  "obtainable": 2,
  "deplete": 1,
  "hunger": 5,
  "bar": 3,
  "zero": 1,
  "empty": 10,
  "depleted": 1,
  "sprinting": 2,
  "jumping": 2,
  "structures": 10,
  "variants": 3,
  "leave": 1,
  "standing": 2,
  "bring": 6,
  "food": 2,
  "steak": 1,
  "regenerate": 1,
  "refill": 1,
  "white": 10,
  "shearing": 1,
  "dyes": 2,
  "azure": 1,
  "bluets": 1,
  "gray": 4,
  "squid": 3,
  "black": 4,
  "ink": 3,
  "sac": 3,
  "combine": 2,
  "cocoa": 2,
  "beans": 2,
  "brown": 3,
  "poppy": 1,
  "dandelion": 1,
  "yellow": 2,
  "orange": 3,
  "cactus": 3,
  "green": 5,
  "lime": 1,
  "cornflower": 1,
  "blue": 5,
  "cyan": 1,
  "purple": 1,
  "allium": 1,
  "magenta": 1,
  "pink": 2,
  "colored": 2,
  "buying": 8,
  "shepherd": 2,
  "mansion": 8,
  "natural": 2,
  "dying": 2,
  "latter": 3,
  "option": 2,
  "fueled": 1,
  "wart": 3,
  "cream": 4,
  "slimeball": 4,
  "input": 11,
  "output": 11,
  "add": 5,
  "awkward": 4,
  "master-level": 4,
  "fletcher": 2,
  "aiming": 1,
  "foundation": 1,
  "filled": 5,
  "want": 3,
  "cut": 5,
  "generator": 2,
  "effiency": 1,
  "risking": 1,
  "pickaxes": 1,
  "carved": 3,
  "pumpkin": 4,
  "jack": 1,
  "o'lantern": 1,
  "pumpkins": 2,
  "chestplate": 5,
  "leggings": 4,
  "outdoor": 1,
  "armory": 1,
  "bought": 8,
  "armorer": 3,
  "vindicators": 1,
  "pillagers": 2,
  "raids": 7,
  "weakness": 14,
  "pressing": 4,
  "process": 5,
  "called": 1,
  "curing": 3,
  "igloo": 2,
  "designed": 1,
  "specifically": 1,
  "basements": 2,
  "cage": 4,
  "simply": 7,
  "bars": 2,
  "maximum": 1,
  "cured": 2,
  "granted": 7,
  "still": 5,
  "besides": 1,
  "church": 1,
  "fermented": 1,
  "eye": 4,
  "bottles": 6,
  "performed": 2,
  "gunpowder": 6,
  "creepers": 2,
  "dungeons": 3,
  "reason": 1,
  "lingering": 2,
  "dispensers": 1,
  "that's": 2,
  "reasons": 2,
  "potentially": 3,
  "lasts": 3,
  "shorter": 1,
  "apples": 3,
  "variant": 1,
  "kills": 1,
  "depends": 4,
  "sunlight": 3,
  "during": 8,
  "successfully": 1,
  "trapping": 2,
  "takes": 7,
  "accelerated": 1,
  "beds": 4,
  "reduces": 1,
  "waiting": 1,
  "ocelots": 2,
  "gained": 1,
  "flee": 1,
  "striders": 2,
  "feather": 3,
  "bows": 2,
  "dealt": 1,
  "consisting": 1,
  "cap": 2,
  "tunic": 2,
  "pants": 2,
  "requiers": 1,
  "dyed": 2,
  "rain": 5,
  "flowers": 4,
  "adding": 7,
  "slimeballs": 3,
  "slimes": 2,
  "sneezing": 1,
  "panda": 1,
  "achieve": 2,
  "wide": 2,
  "etc": 1,
  "skull": 2,
  "big": 2,
  "platform": 2,
  "increase": 2,
  "heads": 2,
  "blowing": 1,
  "weak": 1,
  "ranged": 1,
  "protect": 1,
  "roof": 5,
  "thunderstorm": 3,
  "starts": 6,
  "weather": 1,
  "changed": 2,
  "thunder": 1,
  "channeling": 2,
  "tridents": 3,
  "added": 1,
  "enchanting": 7,
  "transformed": 1,
  "exploding": 2,
  "soon": 4,
  "hisses": 1,
  "run": 2,
  "aware": 3,
  "extremely": 1,
  "helpful": 1,
  "supported": 1,
  "maps": 15,
  "actually": 1,
  "locator": 1,
  "compass": 1,
  "required": 4,
  "cheapest": 1,
  "wasting": 1,
  "cartography": 4,
  "scale": 1,
  "explore": 2,
  "center": 2,
  "completely": 2,
  "arranged": 1,
  "random": 1,
  "design": 2,
  "similar": 2,
  "machine": 12,
  "matching": 3,
  "pistons": 3,
  "extend": 3,
  "retract": 1,
  "gets": 1,
  "pulled": 1,
  "savannas": 2,
  "adult": 4,
  "right-clicking": 2,
  "knock": 1,
  "trying": 1,
  "bucks": 1,
  "carrots": 4,
  "cheaper": 1,
  "breathing": 8,
  "bubble": 10,
  "column": 11,
  "drink": 3,
  "whirlpool": 1,
  "columns": 2,
  "trenches": 1,
  "cavern": 1,
  "brewed": 1,
  "pufferfish": 4,
  "fished": 1,
  "non": 1,
  "provide": 1,
  "downward": 2,
  "align": 1,
  "whilst": 1,
  "tedious": 1,
  "doing": 1,
  "ceiling": 1,
  "cooking": 1,
  "require": 2,
  "guardians": 8,
  "monument": 10,
  "monuments": 5,
  "searching": 2,
  "explorer": 13,
  "journeyman": 4,
  "depth": 2,
  "maze": 1,
  "fatigue": 1,
  "ii": 2,
  "details": 2,
  "sponges": 1,
  "wet": 1,
  "blast": 2,
  "filling": 2,
  "pools": 1,
  "lava-filled": 1,
  "something": 4,
  "dragon's": 4,
  "lands": 2,
  "breathes": 1,
  "magic": 1,
  "currently": 1,
  "bug": 1,
  "awards": 1,
  "randomly": 1,
  "straight": 6,
  "little": 1,
  "looking": 3,
  "fountain": 1,
  "respawning": 2,
  "crystals": 6,
  "surround": 1,
  "tear": 3,
  "surrounded": 2,
  "connecting": 1,
  "crystal": 2,
  "lines": 1,
  "example": 1,
  "configuration": 1,
  "shown": 3,
  "arrangement": 1,
  "end's": 1,
  "respawns": 1,
  "sequence": 2,
  "turns": 1,
  "towers": 1,
  "regenerating": 1,
  "reborn": 1,
  "happens": 2,
  "haven't": 1,
  "collected": 2,
  "yet": 3,
  "upwards": 1,
  "levitation": 1,
  "tall": 3,
  "tower": 7,
  "hits": 1,
  "higher": 6,
  "firework": 3,
  "tricky": 1,
  "chorus": 4,
  "bullets": 1,
  "constantly": 1,
  "hitting": 2,
  "wears": 1,
  "glide": 2,
  "intend": 1,
  "land": 3,
  "falling": 6,
  "generating": 2,
  "guarded": 1,
  "utilize": 1,
  "bullet": 1,
  "vertically": 1,
  "ladders": 2,
  "less": 4,
  "hole": 4,
  "wish": 1,
  "second": 7,
  "boosts": 1,
  "rocket": 1,
  "gateway": 1,
  "z": 2,
  "axes": 3,
  "directions": 2,
  "birds-eye": 1,
  "highlights": 1,
  "standard": 1,
  "sun": 1,
  "rises": 1,
  "east": 1,
  "sets": 1,
  "west": 1,
  "vice": 1,
  "versa": 1,
  "moon": 1,
  "sells": 1,
  "location": 3,
  "boats": 1,
  "shells": 2,
  "shulkers": 2,
  "shell": 2,
  "rename": 1,
  "text": 1,
  "renaming": 1,
  "cost": 1,
  "totems": 2,
  "evokers": 7,
  "third": 4,
  "floor": 3,
  "drinking": 3,
  "captains": 4,
  "outpost": 4,
  "ejected": 3,
  "waves": 2,
  "tough": 1,
  "vexes": 3,
  "offhand": 1,
  "wave": 1,
  "via": 1,
  "omen": 12,
  "entering": 2,
  "levels": 1,
  "beware": 1,
  "fang": 1,
  "strong": 2,
  "raiding": 1,
  "illagers": 2,
  "iceberg": 2,
  "freezes": 2,
  "spotted": 1,
  "tunnels": 1,
  "freeze": 1,
  "transform": 1,
  "frosted": 1,
  "leash": 3,
  "form": 1,
  "baby": 2,
  "counted": 1,
  "caravans": 1,
  "prefer": 1,
  "dolphins": 2,
  "temperatures": 1,
  "keep": 5,
  "mind": 3,
  "deserts": 1,
  "abundantly": 1,
  "rarer": 1,
  "occasions": 1,
  "visible": 1,
  "undamaged": 1,
  "noticeable": 1,
  "due": 1,
  "coral": 1,
  "reefs": 1,
  "making": 3,
  "distinguish": 1,
  "feeding": 2,
  "live": 1,
  "aquatic": 1,
  "includes": 3,
  "aquifers": 1,
  "accidentally": 2,
  "catching": 2,
  "tropical": 1,
  "rewarded": 4,
  "beaches": 2,
  "shores": 1,
  "marked": 1,
  "never": 1,
  "losing": 1,
  "oxygen": 1,
  "caverns": 2,
  "grants": 3,
  "indefinitely": 1,
  "active": 1,
  "convert": 1,
  "gui": 1,
  "launched": 2,
  "raining": 1,
  "mugs": 1,
  "stops": 2,
  "located": 2,
  "leads": 1,
  "prismarine": 13,
  "lanterns": 3,
  "conduits": 1,
  "shard": 5,
  "traders": 1,
  "construction": 5,
  "acquiring": 2,
  "quantities": 1,
  "temple": 1,
  "caught": 1,
  "supply": 1,
  "save": 2,
  "approaches": 1,
  "entity": 1,
  "interaction": 1,
  "range": 2,
  "emit": 1,
  "love": 1,
  "gives": 2,
  "jungles": 2,
  "manually": 1,
  "thing": 2,
  "pattern": 1,
  "emblazons": 1,
  "mojang": 1,
  "logo": 1,
  "population": 1,
  "capped": 1,
  "funneled": 1,
  "sent": 1,
  "somewhere": 2,
  "ravagers": 3,
  "later": 2,
  "triggered": 1,
  "blocking": 2,
  "shield": 1,
  "stun": 1,
  "roar": 1,
  "knockbacking": 1,
  "crossbow": 2,
  "dies": 3,
  "hero": 3,
  "reduced": 2,
  "prices": 1,
  "grindstones": 1,
  "slabs": 1,
  "stonecutter": 3,
  "cutting": 2,
  "slab": 2,
  "meeting": 1,
  "rung": 2,
  "projectiles": 2,
  "bells": 1,
  "sold": 1,
  "toolsmith": 3,
  "weaponsmith": 2,
  "breaking": 4,
  "his": 1,
  "patrols": 1,
  "distinguished": 1,
  "plus": 1,
  "discount": 1,
  "lowering": 1,
  "necessary": 3,
  "exchange": 2,
  "thousand": 1,
  "huge": 2,
  "crop": 2,
  "farmers": 1,
  "restock": 1,
  "composters": 1,
  "assign": 1,
  "profession": 1,
  "additionally": 1,
  "bred": 1,
  "existing": 1,
  "beetroots": 1,
  "potatoes": 1,
  "melon": 3,
  "slices": 1,
  "apprentice": 1,
  "stack": 1,
  "expert": 1,
  "campfires": 2,
  "stem": 2,
  "hyphae": 2,
  "nests": 2,
  "fixed": 1,
  "honeycombs": 3,
  "honeycomb": 4,
  "claims": 1,
  "include": 2,
  "campfire's": 1,
  "smoke": 1,
  "reaches": 2,
  "hive": 2,
  "indicated": 1,
  "texture": 3,
  "dripping": 2,
  "pollinate": 1,
  "roses": 1,
  "flowering": 2,
  "azaleas": 1,
  "azalea": 3,
  "leaves": 1,
  "propagules": 1,
  "spore": 1,
  "blossoms": 1,
  "rest": 1,
  "lost": 1,
  "thus": 2,
  "guarantee": 2,
  "aren't": 1,
  "angry": 3,
  "otherwise": 1,
  "escape": 1,
  "means": 2,
  "nest's": 1,
  "tooltip": 1,
  "touching": 1,
  "slows": 1,
  "tracks": 1,
  "unpredictable": 1,
  "attempts": 1,
  "spaces": 1,
  "collides": 1,
  "couple": 2,
  "hay": 1,
  "bale": 1,
  "targets": 1,
  "unlike": 1,
  "matter": 1,
  "upgrades": 2,
  "netherrack": 2,
  "remnant": 5,
  "armorsmith": 1,
  "tables": 2,
  "trail": 5,
  "exclusively": 2,
  "guaranteed": 2,
  "seven": 2,
  "duplicated": 1,
  "become": 1,
  "aggressive": 1,
  "clock": 2,
  "gilded": 1,
  "glistering": 1,
  "slice": 1,
  "weighted": 1,
  "pressure": 1,
  "plate": 1,
  "gold-related": 1,
  "force": 1,
  "begin": 1,
  "granting": 2,
  "admiring": 1,
  "crimson": 1,
  "tab": 1,
  "entered": 1,
  "locate": 3,
  "animal": 1,
  "enters": 1,
  "underneath": 1,
  "pair": 1,
  "indicate": 2,
  "refilled": 1,
  "ref": 1,
  "remember": 2,
  "results": 1,
  "pre-waxed": 1,
  "scrape": 1,
  "had": 1,
  "oxidized": 1,
  "occasionally": 1,
  "beneath": 1,
  "preparing": 1,
  "respiration": 1,
  "strictly": 1,
  "theory": 1,
  "release": 1,
  "one-shots": 1,
  "sweeping": 1,
  "regeneration": 2,
  "playing": 6,
  "dead": 1,
  "state": 2,
  "enemy": 1,
  "axolotls": 1,
  "retaliate": 1,
  "applied": 2,
  "usual": 2,
  "accessible": 1,
  "involves": 1,
  "access": 2,
  "accessed": 1,
  "write": 1,
  "corresponding": 1,
  "idea": 1,
  "choose": 1,
  "unlikely": 1,
  "scenario": 1,
  "encountering": 1,
  "amethyst": 5,
  "geode": 1,
  "budding": 2,
  "clusters": 1,
  "present": 1,
  "clicking": 1,
  "message": 1,
  "reached": 1,
  "chamber": 3,
  "setup": 4,
  "solid": 1,
  "miss": 2,
  "consuming": 1,
  "endgame": 1,
  "starting": 3,
  "begins": 1,
  "equip": 1,
  "off-hand": 1,
  "important": 2,
  "exactly": 2,
  "degrees": 1,
  "fireworks": 2,
  "mouse": 1,
  "flight": 1,
  "void": 7,
  "midair": 1,
  "shallow": 1,
  "surviving": 2,
  "completing": 1,
  "transport": 1,
  "transported": 2,
  "variety": 1,
  "vertical": 1,
  "benefit": 1,
  "constructed": 1,
  "specific": 2,
  "described": 1,
  "completed": 1,
  "space": 1,
  "according": 1,
  "screenshot": 1,
  "observers": 2,
  "upper": 1,
  "finished": 1,
  "unemployed": 1,
  "job": 1,
  "site": 1,
  "lowest": 1,
  "obviously": 1,
  "pour": 1,
  "serves": 1,
  "landing": 1,
  "pad": 1,
  "flushes": 1,
  "activating": 1,
  "carrying": 1,
  "automatically": 2,
  "perform": 2,
  "safely": 1,
  "observer": 2,
  "disassemble": 1,
  "attach": 1,
  "swung": 1,
  "interact": 1,
  "nineteen": 1,
  "discs": 2,
  "twelve": 1,
  "pigstep": 1,
  "otherside": 1,
  "fragments": 1,
  "relic": 1,
  "brushed": 4,
  "precipice": 1,
  "creator": 2,
  "pots": 2,
  "fungus": 1,
  "chunks": 1,
  "loaded": 1,
  "continuously": 1,
  "reservoir": 1,
  "mid-way": 1,
  "accounts": 2,
  "horizontal": 1,
  "displacement": 1,
  "circle": 1,
  "walks": 1,
  "progress": 1,
  "reset": 1,
  "mounted": 1,
  "sensors": 2,
  "creates": 1,
  "attracting": 1,
  "warden": 2,
  "passive": 2,
  "replacing": 1,
  "cakes": 2,
  "jail": 2,
  "cells": 1,
  "cages": 1,
  "quite": 3,
  "allays": 2,
  "identical": 1,
  "awarding": 1,
  "types": 4,
  "froglight": 6,
  "cubes": 3,
  "eaten": 1,
  "frogs": 4,
  "frog": 13,
  "verdant": 1,
  "ochre": 1,
  "temperate": 1,
  "pearlescent": 1,
  "frogspawn": 1,
  "tadpoles": 1,
  "hatch": 3,
  "moderate": 1,
  "categories": 1,
  "tadpole": 4,
  "grows": 2,
  "sped": 2,
  "passed": 1,
  "suffocating": 1,
  "event": 1,
  "suffocate": 1,
  "preventing": 1,
  "suffocation": 1,
  "repeat": 1,
  "procedure": 1,
  "encase": 1,
  "exact": 1,
  "rough": 1,
  "reverse": 1,
  "approach": 1,
  "delta": 1,
  "sculk-related": 1,
  "prevents": 1,
  "detecting": 1,
  "scary": 1,
  "know": 1,
  "survival": 17,
  "moss": 4,
  "hatching": 1,
  "sniffers": 4,
  "torchflower": 2,
  "pitcher": 1,
  "pods": 1,
  "grant": 4,
  "allowed": 1,
  "naturally-generated": 1,
  "wells": 1,
  "places": 1,
  "average": 1,
  "sherd": 3,
  "retrieve": 1,
  "trim": 9,
  "six": 1,
  "generic": 1,
  "brushing": 1,
  "duplicate": 1,
  "applying": 1,
  "uses": 1,
  "trims": 2,
  "leveled": 1,
  "nearest": 1,
  "entirely": 1,
  "spiral": 1,
  "staircase": 1,
  "descend": 1,
  "keys": 3,
  "significantly": 1,
  "spawner": 7,
  "sees": 1,
  "effects": 1,
  "transforms": 1,
  "previous": 1,
  "irrelevant": 1,
  "cooldown": 1,
  "inert": 1,
  "regardless": 1,
  "spawners": 3,
  "stronger": 1,
  "numerous": 1,
  "charges": 3,
  "tipped": 1,
  "chaotic": 1,
  "buff": 1,
  "debuff": 1,
  "eject": 1,
  "reward": 1,
  "simplest": 1,
  "dropper": 1,
  "breezes": 1,
  "movement": 1,
  "timing": 1,
  "lets": 1,
  "heavy": 2,
  "core": 2,
  "overall": 1,
  "minimum": 1,
  "density": 1,
  "none": 1,
  "player-built": 1,
  "perfect": 1,
  "candidate": 1,
  "fenced": 1,
  "makes": 1,
  "retaliation": 1,
  "certainly": 1,
  "resin": 7,
  "options": 1,
  "garden": 3,
  "plateaus": 1,
  "leading": 1,
  "appears": 1,
  "clumps": 1,
  "clump": 2,
  "valleys": 1,
  "fossils": 2,
  "happy": 1,
  "unit": 1,
  "material": 1,
  "longest": 1,
  "challenging": 2,
  "keeping": 1,
  "tunnel": 1,
  "mount": 1,
  "available": 1,
  "late-game": 1,
  "row": 1,
  "sprint": 1,
  "unreliable": 1,
  "ai": 1,
  "dungeon": 1,
  "mellohi": 1,
  "re-dyeing": 1,
  "re-dye": 1,
  "adventure": 4,
  "beginner's": 2,
  "tutorials": 1,
  "introductory": 1,
  "basics": 2,
  "glossary": 1,
  "newcomer": 1,
  "ten": 1,
  "management": 1,
  "things": 3,
  "tricks": 1,
  "shelters": 3,
  "homes": 2,
  "general": 5,
  "husbandry": 1,
  "enchantments": 2,
  "chunk": 2,
  "loader": 1,
  "combat": 1,
  "dual": 1,
  "wielding": 1,
  "gathering": 1,
  "max": 1,
  "gear": 1,
  "headless": 1,
  "hitboxes": 1,
  "indestructible": 1,
  "managing": 1,
  "superflat": 2,
  "mapping": 1,
  "measuring": 1,
  "education": 1,
  "hub": 1,
  "organization": 1,
  "phantom-proofing": 1,
  "spawn-proofing": 1,
  "summoning": 1,
  "jockeys": 1,
  "bored": 1,
  "time-saving": 1,
  "transportation": 4,
  "units": 1,
  "measure": 1,
  "mechanics": 5,
  "x-ray": 1,
  "glitches": 2,
  "siege": 1,
  "defense": 2,
  "automatic": 2,
  "manual": 1,
  "challenges": 2,
  "archaeology": 1,
  "conquering": 1,
  "mastering": 2,
  "escapes": 1,
  "locating": 1,
  "non-standard": 1,
  "custom": 10,
  "ultra": 1,
  "hearted": 1,
  "infinite": 1,
  "island": 1,
  "manhunt": 1,
  "nomadic": 1,
  "skyblock": 1,
  "skywars": 1,
  "speedrunning": 1,
  "border": 1,
  "challenge": 3,
  "beating": 1,
  "constructions": 3,
  "beauty": 1,
  "airlock": 1,
  "architectural": 1,
  "terms": 1,
  "cruise": 1,
  "ship": 1,
  "metropolis": 1,
  "rollercoaster": 1,
  "micro": 1,
  "safe": 1,
  "features": 1,
  "ban": 1,
  "palette": 1,
  "shapes": 1,
  "elevators": 1,
  "endless": 1,
  "circling": 1,
  "furniture": 1,
  "glazed": 1,
  "terracotta": 1,
  "patterns": 1,
  "nice": 1,
  "floors": 1,
  "pixel": 1,
  "art": 1,
  "ranches": 1,
  "guidelines": 1,
  "secret": 1,
  "door": 1,
  "settlement": 1,
  "buttresses": 1,
  "water-powered": 1,
  "igniting": 1,
  "farming": 5,
  "fern": 1,
  "glow": 4,
  "berries": 2,
  "lichen": 1,
  "horn": 1,
  "hanging": 1,
  "roots": 1,
  "mud": 1,
  "vine": 2,
  "snow": 3,
  "rooted": 1,
  "turtle": 2,
  "scute": 1,
  "seagrass": 1,
  "sweet": 1,
  "hall": 1,
  "rose": 1,
  "duplication": 2,
  "grinding": 1,
  "traps": 2,
  "animals": 1,
  "mechanisms": 2,
  "circuits": 3,
  "components": 2,
  "command": 3,
  "tripwire": 1,
  "techniques": 1,
  "detector": 3,
  "quasi-connectivity": 1,
  "randomizers": 1,
  "stabilizer": 1,
  "update": 5,
  "comparator": 1,
  "telegraph": 1,
  "zero-ticking": 1,
  "instant": 2,
  "repeaters": 1,
  "morse": 1,
  "code": 2,
  "decorational": 1,
  "doorbell": 1,
  "hourly": 1,
  "train": 1,
  "machines": 1,
  "cannon": 1,
  "storage": 4,
  "sorting": 1,
  "system": 2,
  "pvp": 2,
  "cannons": 1,
  "logic": 2,
  "advanced": 1,
  "arithmetic": 1,
  "calculator": 1,
  "computers": 1,
  "miscellaneous": 1,
  "printer": 1,
  "rube": 1,
  "goldberg": 1,
  "stats": 1,
  "anchor": 1,
  "recharger": 1,
  "combination": 1,
  "locks": 1,
  "griefing": 1,
  "prevention": 1,
  "hiding": 1,
  "servers": 1,
  "bases": 1,
  "joining": 1,
  "lan": 2,
  "alternate": 1,
  "server": 8,
  "forge": 2,
  "hamachi": 1,
  "maintenance": 1,
  "technical": 1,
  "mods": 1,
  "improving": 1,
  "rate": 1,
  "faq": 1,
  "studio": 1,
  "programs": 1,
  "editors": 1,
  "running": 1,
  "data": 10,
  "downgrading": 1,
  "restoring": 1,
  "profiles": 1,
  "launcher": 2,
  "commands": 1,
  "importing": 2,
  "exporting": 1,
  "nbt": 1,
  "tags": 1,
  "updating": 1,
  "mcedit": 1,
  "resource": 3,
  "loading": 1,
  "models": 1,
  "directory": 2,
  "panoramas": 1,
  "dimension": 1,
  "paintings": 1,
  "repairing": 1,
  "corrupted": 2,
  "media": 1,
  "videos": 1,
  "livestreaming": 1,
  "ip": 1,
  "installation": 1,
  "installing": 2,
  "versions": 2,
  "preview": 1,
  "beta": 1,
  "crash": 2,
  "report": 2,
  "saving": 2,
  "thumb": 2,
  "drive": 3,
  "recover": 1,
  "saved": 2,
  "google": 1,
  "dropbox": 2,
  "mac": 1,
  "os": 1,
  "startup": 1,
  "daemon": 1,
  "chromeos": 1,
  "outdated": 1,
  "door-based": 1,
  "pre": 1,
  "chaining": 1,
  "contraptions": 1,
  "booster": 1,
  "repeater": 1,
  "reboot": 1,
  "wire": 1,
  "ladder": 1,
  "tram": 1,
  "enabled": 1,
  "man-made": 1,
  "spigot": 1,
  "lwjgl": 1,
  "generation": 1
}